[
  {
    "id": "98e0a0cf-d910-42fa-b0ab-93093274e906",
    "hotel_name": "HOTEL Z (ホテル ゼット)【SLPホテルズ】",
    "amenities": [
      "持込用冷蔵庫",
      "電子レンジ",
      "電気ポット",
      "加湿器",
      "空気清浄機",
      "マッサージチェア※一部",
      "お姫様(天蓋)ベッド※一部",
      "水中照明※一部",
      "ジェット・バブルバス※一部",
      "ウォシュレット",
      "岩盤浴※一部",
      "VOD",
      "Wi-Fi",
      "Android充電器※一部",
      "iPhone充電器※一部",
      "DVDプレーヤー※一部",
      "セレクトシャンプー",
      "カールドライヤー",
      "ヘアアイロン",
      "電気マッサージ器※一部"
    ],
    "prices": {
      "宿泊": [
        {
          "title": "[日～金1部]",
          "price": "7980円～9580円",
          "time": "（ 21:00～翌12:00 最大15時間 ）"
        },
        {
          "title": "[日～金2部]",
          "price": "7980円～9580円",
          "time": "（ 00:00～14:00 最大14時間 ）"
        },
        {
          "title": "[土・祝前・特別日1部]",
          "price": "10980円～12980円",
          "time": "（ 22:00～翌10:00 最大12時間 ）"
        },
        {
          "title": "[土・祝前・特別日2部]",
          "price": "10980円～12980円",
          "time": "（ 00:00～12:00 最大12時間 ）"
        }
      ],
      "休憩": [
        {
          "title": "[月～金（ショート）]",
          "price": "4580円～5580円",
          "time": "（ 24時間制 滞在時間2時間 ）"
        },
        {
          "title": "[月～金（3時間）]",
          "price": "5080円～6080円",
          "time": "（ 24時間制 滞在時間3時間 ）"
        },
        {
          "title": "[土・日・祝（ショート）]",
          "price": "5080円～6080円",
          "time": "（ 24時間制 滞在時間2時間 ）"
        },
        {
          "title": "[土・日・祝（3時間）]",
          "price": "5580円～6580円",
          "time": "（ 24時間制 滞在時間3時間 ）"
        }
      ],
      "サービスタイム": [
        {
          "title": "[月～金1部]",
          "price": "5580円～6580円",
          "time": "（ 05:00～12:00 チェックインより 滞在時間8時間 ）"
        },
        {
          "title": "[月～金2部]",
          "price": "5580円～6580円",
          "time": "（ 12:00～17:00 チェックインより 滞在時間6時間 ）"
        },
        {
          "title": "[月～金3部]",
          "price": "5580円～6580円",
          "time": "（ 17:00～21:00 チェックインより 滞在時間4時間 ）"
        },
        {
          "title": "[土・日・祝1部]",
          "price": "6080円～6980円",
          "time": "（ 05:00～12:00 チェックインより 滞在時間6時間 ）"
        },
        {
          "title": "[土・日・祝2部]",
          "price": "6080円～6980円",
          "time": "（ 12:00～17:00 チェックインより 滞在時間4時間 ）"
        }
      ],
      "延長料金": [
        {
          "title": "[全日]",
          "price": "1000円",
          "time": ""
        }
      ]
    },
    "reviews": [
      "お部屋も広く、ガレージタイプのため、お部屋から車への移動がかなり楽でした。\nお風呂も広々としていて、ゆっくりと過ごせます。",
      "はじめて利用しましたが、お部屋がとても広く、そしてきれいで驚きました！\n値段も手ごろで、ゆったりと過ごすことができました。\nぜひまた利用したいと思います！"
    ]
  },
  {
    "id": "02318149-cdb9-4bb1-99b5-229e8d2748bc",
    "hotel_name": "ホテル  モナコ",
    "amenities": [],
    "prices": {},
    "reviews": []
  },
  {
    "id": "ffcd2f92-39e9-43cc-bf69-0d2c09c0ae0a",
    "hotel_name": "HOTEL ME",
    "amenities": [
      "持込用冷蔵庫",
      "電子レンジ",
      "空気清浄機",
      "ブラックライト※一部",
      "マッサージチェア※一部",
      "浴室TV",
      "水中照明",
      "ジェット・バブルバス",
      "マット※一部",
      "ウォシュレット",
      "ミストサウナ※一部",
      "ホームシアター",
      "カラオケ",
      "プロジェクター※一部",
      "VOD",
      "Wi-Fi",
      "Android充電器",
      "iPhone充電器",
      "ブルーレイプレーヤー",
      "セレクトシャンプー"
    ],
    "prices": {
      "宿泊": [
        {
          "title": "[日～木・祝日]",
          "price": "7950円～11400円",
          "time": "（ 20:00～翌12:00 ）"
        },
        {
          "title": "[金]",
          "price": "7950円～11400円",
          "time": "（ 20:00～翌12:00 ）"
        },
        {
          "title": "[土・祝前日]",
          "price": "9380円～13030円",
          "time": "（ 22:00～翌11:00 ）"
        }
      ],
      "休憩": [
        {
          "title": "[月～金]",
          "price": "5310円～7540円",
          "time": "（ 05:00～24:00 滞在時間4時間 ）"
        },
        {
          "title": "[土･日・祝日]",
          "price": "5310円～7540円",
          "time": "（ 05:00～24:00 滞在時間3時間 ）"
        }
      ],
      "サービスタイム": [
        {
          "title": "[月～金1部]",
          "price": "5310円～7540円",
          "time": "（ 05:00～17:00 滞在時間12時間 ）"
        },
        {
          "title": "[月～金2部]",
          "price": "5310円～7540円",
          "time": "（ 10:00～21:00 ＩＮ/最大7時間滞在 ）"
        },
        {
          "title": "[土・日・祝日1部]",
          "price": "5310円～7540円",
          "time": "（ 05:00～15:00 滞在時間10時間 ）"
        },
        {
          "title": "[土・日・祝日2部]",
          "price": "5310円～7540円",
          "time": "（ 10:00～20:00 ＩＮ/最大5時間滞在 ）"
        }
      ],
      "延長料金": [
        {
          "title": "[全日]",
          "price": "1050円～1230円",
          "time": ""
        }
      ]
    },
    "reviews": [
      "白を基調としてて清潔感あって落ち着いたし良かったです。また来たいと思います（＾∇＾）",
      "ずっといちゃいちゃして幸せな１日でした。\nお部屋も綺麗でアメニティーも充実しててまた来ようねって約束してきました。"
    ]
  },
  {
    "id": "6244d387-321c-4c4f-bcc5-b0fe7670c21e",
    "hotel_name": "HOTEL LUNA",
    "amenities": [
      "豊富にレンタルアメニティーをご用意しております。"
    ],
    "prices": {
      "宿泊": [],
      "休憩": [],
      "サービスタイム": [],
      "延長料金": []
    },
    "reviews": [
      "緊張しながら初めて利用した。また利用したい",
      "温水ではなかった、冷たくて泳ぎを楽しむどろではない！\nフロントへクレームつけると予約時に承知済みのはずだと心ない返事、そんな事は聞いてないし水だと聞いたら予約なんかしない。\n仕方なくバケツを持ってきてもらい風呂のお湯をプールへ入れるがたいした効果なく冷たいまま。\nあとプール入る梯子が付いてない、手すりはグラグラし外れそうだ。\nこれまた仕方なく脚立を持ってきてもらい沈めて手すりに横付け、プールの写真にはちゃんと梯子は付いてる。水中に沈めた脚立から落ちて怪我しても責任は負わないと心外な返事。梯子外した事の責任はどっか行ってしまったようだ。\n翌日自動精算機で正規の料金を支払いチェックアウト。\n\nこんな心ないホテルはもう二度と利用しないから覚えておけ！！！"
    ]
  },
  {
    "id": "d4cbca9b-8a34-4fdc-af48-5d7f96d26e2a",
    "hotel_name": "HOTEL SOL",
    "amenities": [
      "持込用冷蔵庫",
      "電子レンジ",
      "電気ポット",
      "加湿器※一部",
      "空気清浄機",
      "浴室TV※一部",
      "ジェット・バブルバス",
      "ウォシュレット",
      "VOD",
      "Wi-Fi",
      "有線LAN",
      "Android充電器",
      "iPhone充電器",
      "DVDプレーヤー",
      "ブルーレイプレーヤー",
      "クロームキャスト",
      "セレクトシャンプー",
      "カールドライヤー",
      "ヘアアイロン",
      "電気マッサージ器"
    ],
    "prices": {
      "宿泊": [
        {
          "title": "[日～木・祝]",
          "price": "6340円～7330円",
          "time": "（ 20:00～翌12:00 ）"
        },
        {
          "title": "[金]",
          "price": "6980円～8070円",
          "time": "（ 20:00～翌12:00 ）"
        },
        {
          "title": "[土・祝前]",
          "price": "9270円～10720円",
          "time": "（ 20:00～翌11:00 ）"
        }
      ],
      "休憩": [
        {
          "title": "[月～金（2時間）]",
          "price": "3190円～3900円",
          "time": "（ 06:00～翌25:00 滞在時間2時間 ）"
        },
        {
          "title": "[月～金（4時間）]",
          "price": "3830円～4690円",
          "time": "（ 06:00～翌25:00 滞在時間4時間 ）"
        },
        {
          "title": "[土・日・祝・祝前（2時間）]",
          "price": "4320円～5270円",
          "time": "（ 06:00～翌25:00 滞在時間2時間 ）"
        },
        {
          "title": "[土・日・祝・祝前（4時間）]",
          "price": "5170円～6330円",
          "time": "（ 06:00～翌25:00 滞在時間4時間 ）"
        }
      ],
      "サービスタイム": [
        {
          "title": "[月～金]",
          "price": "4150円～5080円",
          "time": "（ 06:00～18:00 滞在時間12時間 ）"
        },
        {
          "title": "[月～金（SUPERフリータイム）]",
          "price": "5110円～6240円",
          "time": "（ 06:00～24:00 滞在時間18時間 ）"
        },
        {
          "title": "[土・日・祝・祝前]",
          "price": "5600円～6860円",
          "time": "（ 06:00～17:00 滞在時間11時間 ）"
        },
        {
          "title": "[土・日・祝・祝前（SUPERフリータイム）]",
          "price": "6470円～7900円",
          "time": "（ 06:00～20:00 滞在時間14時間 ）"
        }
      ],
      "延長料金": [
        {
          "title": "[月～金(15分単位)]",
          "price": "500円",
          "time": ""
        },
        {
          "title": "[土・日・祝・祝前(15分単位)]",
          "price": "550円",
          "time": ""
        }
      ]
    },
    "reviews": [
      "駐車場のプロジェクターに感動した！ほんとすごい！駐車場と廊下とかが綺麗だった分、部屋が普通だったのが残念だった。ウェルカムスイーツがいきなりドア開けられて届けられたから、いちゃいちゃ中だったしビックリした。",
      "GWだったのでクーポンの特典が使えるか不安でしたが、問い合わせ時に「大丈夫ですよ」と丁寧に対応してもらい気持ち良く利用できました。\nお部屋は必要なものをコンパクトにまとめた使いやすい内装でした。掃除も細かい所まで行き届いていて綺麗な印象でした。"
    ]
  },
  {
    "id": "e557c49d-1781-4ff5-95aa-702ed537be61",
    "hotel_name": "ホテル 雅",
    "amenities": [
      "持込用冷蔵庫",
      "電子レンジ",
      "電気ポット",
      "加湿器※一部",
      "空気清浄機",
      "ブラックライト※一部",
      "マッサージチェア※一部",
      "水中照明",
      "ジェット・バブルバス",
      "マット※一部",
      "ウォシュレット",
      "露天風呂※一部",
      "ミストサウナ※一部",
      "ホームシアター※一部",
      "プロジェクター※一部",
      "Wi-Fi",
      "有線LAN",
      "Android充電器",
      "iPhone充電器",
      "DVDプレーヤー"
    ],
    "prices": {
      "宿泊": [
        {
          "title": "[月～木1部]",
          "price": "5900円～22000円",
          "time": "（ 13:00～16:59 in 翌12:00 out / 最大23時間 ）"
        },
        {
          "title": "[月～木2部]",
          "price": "5900円～22000円",
          "time": "（ 17:00～22:59 in 翌15:00 out / 最大22時間 ）"
        },
        {
          "title": "[月～木3部]",
          "price": "5900円～22000円",
          "time": "（ 23:00～翌04:59 in 翌18:00 out / 最大19時間 ）"
        },
        {
          "title": "[金曜1部]",
          "price": "6900円～13500円",
          "time": "（ 13:00～16:59 in 翌11:00 out / 最大22時間 ）"
        },
        {
          "title": "[金曜2部]",
          "price": "6900円～13500円",
          "time": "（ 17:00～22:59 in 翌12:00 out / 最大19時間 ）"
        },
        {
          "title": "[金曜3部]",
          "price": "6900円～13500円",
          "time": "（ 23:00～翌04:59 in 翌13:00 out / 最大14時間 ）"
        },
        {
          "title": "[土・祝前1部]",
          "price": "8900円～25000円",
          "time": "（ 19:00～22:59 in 翌10:00 out / 最大15時間 ）"
        },
        {
          "title": "[土・祝前2部]",
          "price": "8900円～25000円",
          "time": "（ 23:00～翌04:59 in 翌12:00 out / 最大13時間 ）"
        },
        {
          "title": "[日・祝1部]",
          "price": "5900円～22000円",
          "time": "（ 15:00～16:59 in 翌12:00 out / 最大21時間 ）"
        },
        {
          "title": "[日・祝2部]",
          "price": "5900円～22000円",
          "time": "（ 17:00～22:59 in 翌15:00 out / 最大22時間 ）"
        },
        {
          "title": "[日・祝3部]",
          "price": "5900円～22000円",
          "time": "（ 23:00～翌04:59 in 翌18:00 out / 最大19時間 ）"
        }
      ],
      "休憩": [
        {
          "title": "[月～金(ショート)]",
          "price": "2500円～8000円",
          "time": "（ 24時間制 滞在時間120分 ）"
        },
        {
          "title": "[月～金(休憩)]",
          "price": "3500円～10000円",
          "time": "（ 24時間制 滞在時間4時間 ）"
        },
        {
          "title": "[月～金(深夜休憩)]",
          "price": "4000円～12500円",
          "time": "（ 00:00～04:59 滞在時間3時間 ）"
        },
        {
          "title": "[土・祝前(ショート)]",
          "price": "3000円～9000円",
          "time": "（ 05:00～21:59 滞在時間120分 ）"
        },
        {
          "title": "[土・祝前(休憩)]",
          "price": "4000円～11000円",
          "time": "（ 05:00～20:59 滞在時間3時間 ）"
        },
        {
          "title": "[日・祝(ショート)]",
          "price": "3000円～9000円",
          "time": "（ 24時間制 滞在時間120分 ）"
        },
        {
          "title": "[日・祝(休憩)]",
          "price": "4000円～11000円",
          "time": "（ 24時間制 滞在時間3時間 ）"
        }
      ],
      "サービスタイム": [
        {
          "title": "[月～金1部]",
          "price": "4000円～12500円",
          "time": "（ 05:00～08:59 in 滞在時間13時間 ）"
        },
        {
          "title": "[月～金2部]",
          "price": "4000円～12500円",
          "time": "（ 09:00～14:59 in 滞在時間8時間 ）"
        },
        {
          "title": "[月～金3部]",
          "price": "4000円～12500円",
          "time": "（ 15:00～18:00 in 滞在時間6時間 ）"
        },
        {
          "title": "[土・日・祝1部]",
          "price": "4500円～13500円",
          "time": "（ 05:00～08:59 in 滞在時間10時間 ）"
        },
        {
          "title": "[土・日・祝2部]",
          "price": "4500円～13500円",
          "time": "（ 09:00～14:59 in 滞在時間7時間 ）"
        },
        {
          "title": "[土・日・祝3部]",
          "price": "4500円～13500円",
          "time": "（ 15:00～16:59 in 滞在時間5時間 ）"
        }
      ],
      "延長料金": [
        {
          "title": "[月～金]",
          "price": "1000円～2500円",
          "time": ""
        },
        {
          "title": "[土・日・祝]",
          "price": "1500円～3000円",
          "time": ""
        }
      ]
    },
    "reviews": []
  },
  {
    "id": "35ab5ede-9942-4a7c-b8eb-7573f826496e",
    "hotel_name": "ホテル  サンマリン",
    "amenities": [],
    "prices": {},
    "reviews": []
  },
  {
    "id": "0244422e-6a95-40b7-b94d-70a60f09b13a",
    "hotel_name": "HOTEL  SIRENE (ホテル シレーヌ)",
    "amenities": [],
    "prices": {},
    "reviews": [
      "何度か利用させて頂きました。\n我は、スーパー先端クロと申す。先端クロからバージョンアップしました。\nここには4人の男性との思い出があります。\nそれぞれのことを話させていただきたいと思います。\n1人目は特になし。\n2人目と伺った時、ワンナイトラブの相手でしたが恋するフォーチュンクッキーが流れていて行為に集中出来ず、またお相手のシモのセンスがないということで私が威圧し、お相手が避妊具を装着する手が震えていました。\n3人目と伺ったき、アイホンの充電器を借りたいと連絡したところすごい感じの悪いオヤジが怒りながら貸してくださいました。朝ごはんはお重に生ゴミを集めたかのようなご飯で全てお湯の味がしました。味噌汁しかのめず最悪な朝の始まりでした。\n4人目、現在の彼氏です。夜勤明けの彼氏とお風呂に入っていない不潔な私は朝から利用しました。ここでも恋するフォーチュンクッキーが流れていました。お風呂で体を流すだけでなく、お互いガッツリはいりましたが、お湯が浴槽の方しかでなくなり春だったので水のシャワーは使えず、まるで餅つきのように洗面器でお湯を汲み、お互いの頭を流し合いました。......私は見てしまったのです！！！お風呂の浴槽にピンク色の水垢が凄いことを。。。\n全くさっぱりしませんでした。ドライヤーのホコリもすごく、ドライヤーの交換を頼んだのにオヤジがホコリをサッサっと取っただけでした。天井のホコリもすごくほんとに最悪です。ハウスダストアレルギーを発症しますので皆様おきをつけて。"
    ]
  },
  {
    "id": "0852b702-2870-4277-8d1b-cc268299379c",
    "hotel_name": "HOTEL Prestige (ホテル プレステージ)",
    "amenities": [],
    "prices": {},
    "reviews": [
      "部屋は清潔感があり綺麗でした。\nアメニティが少ないので、もう少し充実して欲しい。"
    ]
  },
  {
    "id": "98f9ef5c-c092-47d7-9624-c58fcac45126",
    "hotel_name": "ホテル アラウダリゾート国立",
    "amenities": [],
    "prices": {},
    "reviews": [
      "エントランスから、シックでとても綺麗です。ほんのり、アロマの香りもGood！お部屋やお風呂は、綺麗で結構広いです。",
      "ハンバーグを食べてあまりの美味さにビックリ！帰る時にフロントの人に聞いてみたら…なんと生肉を焼いて提供していると聞かされビックラポン！おまけに石窯ピザもあったので注文したけど素手に売り切れ！前に食べた時に美味しかったから食べたかったのに残念！次に行ったら必ず食べたい一品です。あの辺のラブホでは、一番料理がウマシ！ウマシって感じ。"
    ]
  },
  {
    "id": "bdd42ded-2ee0-491a-bde0-ce303d62d407",
    "hotel_name": "HOTEL LISTO (ホテル リスト)",
    "amenities": [],
    "prices": {},
    "reviews": [
      "サービスプラン2、7,300円で利用。\n可もなく不可もなし。\n部屋によると思うが、古臭さは感じるが清潔感はあるので、優先順位は高くないがリピートはあり。\n\n入口が複数あるので、人目を避けるのには有り難い。\n入口が、階段降りないといけないので、ヒールの人には気を遣ってしまう。",
      "高い部屋はそれなりに良い"
    ]
  },
  {
    "id": "a78da278-994a-4f90-9a23-2c0fef49b0ba",
    "hotel_name": "HOTEL RAMSES CLUB (ホテル ラムセスクラブ)",
    "amenities": [],
    "prices": {},
    "reviews": [
      "数年利用させてもらってて部屋自体は綺麗なんだけど、Wi-Fiが使えない部屋が非常に多い(エラーがでて繋がらない)VODもリモコン操作できず見れない部屋ばかり、日によってはシャワーも尋常じゃないくらい弱い。",
      "立地がホテル街ではないけれど、外観がオシャレなので入りやすかったです。\n室内も素敵なので落ち着いて過ごせました。\nそのわりに料金は高くないので、利用しやすいと思いました。\nまた使いたいです！"
    ]
  },
  {
    "id": "722c2ba8-13eb-41cf-a41d-6e3b8032091c",
    "hotel_name": "アップル  ホテル",
    "amenities": [],
    "prices": {},
    "reviews": [
      "休日のサービスタイムに利用しました。\n全室均一料金で、最後の一部屋でしたが一番広い部屋が残っていてラッキーでした！\n部屋はベッドルームとリビング？の二部屋に分かれていて広くて綺麗でした。\nお風呂も広めで綺麗でした！\nフロントのおば様は、とても親切でした(^-^)\n\n残念だったのは休日だとウェルカムサービス等が何もない事"
    ]
  },
  {
    "id": "605dcb8a-004b-401e-9d74-cdc8999f3e2e",
    "hotel_name": "HOTEL AKAIKUTSU / 横浜市中区",
    "amenities": [],
    "prices": {},
    "reviews": []
  },
  {
    "id": "472a2347-e88d-4469-b256-620af7984c90",
    "hotel_name": "HOTEL  AIM (ホテル アイム)",
    "amenities": [],
    "prices": {},
    "reviews": []
  },
  {
    "id": "e878aebe-9098-489c-8545-7f1c08428579",
    "hotel_name": "HOTEL SKY",
    "amenities": [
      "持込用冷蔵庫",
      "電子レンジ",
      "電気ポット",
      "加湿器",
      "空気清浄機",
      "マッサージチェア※一部",
      "浴室TV",
      "水中照明",
      "ジェット・バブルバス",
      "マット※一部",
      "ウォシュレット",
      "プロジェクター※一部",
      "VOD",
      "Wi-Fi",
      "有線LAN",
      "Android充電器",
      "iPhone充電器",
      "DVDプレーヤー※一部",
      "ブルーレイプレーヤー",
      "セレクトシャンプー※一部"
    ],
    "prices": {
      "宿泊": [
        {
          "title": "[月～木1部]",
          "price": "7140円～11340円",
          "time": "（ 18:00～翌12:00 ）"
        },
        {
          "title": "[月～木2部]",
          "price": "7140円～11340円",
          "time": "（ 00:00～15:00 ）"
        },
        {
          "title": "[金曜1部]",
          "price": "7140円～11340円",
          "time": "（ 18:00～翌11:00 ）"
        },
        {
          "title": "[金曜2部]",
          "price": "7140円～11340円",
          "time": "（ 00:00～13:00 ）"
        },
        {
          "title": "[土・祝前1部]",
          "price": "11500円～16800円",
          "time": "（ 18:00～翌11:00 ）"
        },
        {
          "title": "[土・祝前2部]",
          "price": "11500円～16800円",
          "time": "（ 00:00～13:00 ）"
        },
        {
          "title": "[日・祝1部]",
          "price": "7140円",
          "time": "（ 20:00～翌12:00 ）"
        },
        {
          "title": "[日・祝2部]",
          "price": "7140円",
          "time": "（ 00:00～15:00 ）"
        }
      ],
      "休憩": [
        {
          "title": "[【ショート100分】月～金]",
          "price": "4300円～4700円",
          "time": "（ 06:00～翌01:00 滞在時間100分 ）"
        },
        {
          "title": "[【ショート100分】土・日・祝]",
          "price": "4500円～4900円",
          "time": "（ 06:00～翌02:00 滞在時間100分 ）"
        },
        {
          "title": "[月～木 4時間]",
          "price": "5300円～7900円",
          "time": "（ 06:00～翌01:00 滞在時間4時間 ）"
        },
        {
          "title": "[金・祝前 4時間]",
          "price": "5300円～7900円",
          "time": "（ 06:00～翌02:00 滞在時間4時間 ）"
        },
        {
          "title": "[土曜 3時間]",
          "price": "5500円～8300円",
          "time": "（ 06:00～翌02:00 滞在時間3時間 ）"
        },
        {
          "title": "[日・祝 3時間]",
          "price": "5500円～8300円",
          "time": "（ 06:00～翌01:00 滞在時間3時間 ）"
        }
      ],
      "サービスタイム": [
        {
          "title": "[月～金1部]",
          "price": "5800円～6800円",
          "time": "（ 06:00～18:00 ）"
        },
        {
          "title": "[月～金2部]",
          "price": "5800円～7900円",
          "time": "（ 12:00～21:00 ）"
        },
        {
          "title": "[土・日・祝1部]",
          "price": "6300円～8300円",
          "time": "（ 06:00～16:00 ）"
        },
        {
          "title": "[土・日・祝2部]",
          "price": "6300円～8300円",
          "time": "（ 12:00～20:00 ）"
        }
      ],
      "延長料金": [
        {
          "title": "[全日]",
          "price": "600円",
          "time": ""
        }
      ]
    },
    "reviews": []
  },
  {
    "id": "72079912-8349-44f2-933a-ce37d7b691e0",
    "hotel_name": "DESIGN HOTEL IROHA 六本木 (デザイン ホテル イロハ)",
    "amenities": [],
    "prices": {},
    "reviews": [
      "とても素敵なホテルでした。\nバスタオルは、4枚あればもっと良かったかな。\n後は全て満足でした。\nまた利用させていただきます。",
      "露天風呂のあるお部屋を利用しました◎\nこんな都心にオシャレな露天風呂があってビックリ！\nお部屋も外観に合わせた和モダンなテイストで落ち着きます。\nアメニティや入浴剤も種類は豊富だし、バスローブやガウンやタオルも肌触りの良いものが揃っていてデザインホテルって感じでした。\nまた行きたいです！"
    ]
  },
  {
    "id": "08eda856-de6b-488e-805f-52aab77faed6",
    "hotel_name": "ホテル 禅",
    "amenities": [
      "持込用冷蔵庫※一部",
      "電子レンジ",
      "電気ポット",
      "加湿器",
      "空気清浄機",
      "マッサージチェア※一部",
      "ジェット・バブルバス※一部",
      "マット",
      "ウォシュレット",
      "カラオケ※一部",
      "VOD",
      "Wi-Fi",
      "有線LAN",
      "Android充電器",
      "iPhone充電器",
      "DVDプレーヤー※一部",
      "セレクトシャンプー",
      "カールドライヤー",
      "ヘアアイロン",
      "電気マッサージ器※一部"
    ],
    "prices": {
      "宿泊": [
        {
          "title": "[日～木]",
          "price": "6420円～8500円",
          "time": "（ 16:00～翌12:00 ）"
        },
        {
          "title": "[金]",
          "price": "7450円～9730円",
          "time": "（ 17:00～翌12:00 ）"
        },
        {
          "title": "[土・祝前]",
          "price": "8460円～10800円",
          "time": "（ 19:00～翌11:00 ）"
        }
      ],
      "休憩": [
        {
          "title": "[月～金]",
          "price": "4070円～5600円",
          "time": "（ 06:00～24:00 滞在時間6時間 ）"
        }
      ],
      "サービスタイム": [
        {
          "title": "[土・日・祝日]",
          "price": "4480円～6000円",
          "time": "（ 06:00～24:00 チェックインの時間により滞在時間が変更となります。備考をご確認ください。 ）"
        }
      ],
      "延長料金": [
        {
          "title": "[月～金]",
          "price": "300円",
          "time": ""
        },
        {
          "title": "[土・日・祝前日・祝日]",
          "price": "350円",
          "time": ""
        }
      ]
    },
    "reviews": [
      "ウエルカムドリンクや、アメニティが豊富かつ使いやすい料金プランで今後も機会があれば利用させて頂きたいと思います。",
      "建物は古びてますが、アメニティが充実していて便利です。\n\n他のホテルに比べると料金がお手頃だと感じます。\n選んだプランのおかげかもしれませんが、お正月三が日の宿泊利用でも1万を超えませんでした。\nウェルカムドリンクも嬉しいです。チューハイもちゃんと濃い味でした。\n\n部屋ごとに間取りやデザインも異なっていて、SMルームがあったり、マンガを読める部屋があったり、畳敷きの和風旅館風だったり、と違いも楽しいです。"
    ]
  },
  {
    "id": "24ec5e45-21c0-4ea1-9518-e24dc11f06f2",
    "hotel_name": "HOTEL BIX (ホテル ビックス)",
    "amenities": [],
    "prices": {},
    "reviews": [
      "フロントなどのスタッフ対応は良かったのですが、部屋内の設備が良くありませんでした。\nエアコンの効きはとても悪く、冷蔵庫など何時間入れてても冷えなかったです料金の割には部屋はとても狭くもう利用することはありません。",
      "今回が3度目の利用でした。\nフロントもビジネスホテルのようなシックな佇まいで、接客も良い感じでした。\nお部屋も全室一律料金、内装も落ち着いたデザインで比較的リーズナブルな価格になっています。\n特に日曜・祝日は全体的に価格が安く、チェックアウトも翌11:00となっているため、とてもリーズナブルに泊まることができます。\n\n内装は全体的に綺麗で、お部屋も広すぎず、狭すぎずのちょうどいい広さです。\nお掃除も概ね綺麗にされてますが、お部屋によっては一部壁紙が剥がれている箇所があり、少し残念でした。\nトイレは広く、浴室は同価格帯のホテルよりは広い印象を受けました。\n浴槽も大きめです。\n\n難点は金・土・連休中日の宿泊料金が、平日よりも2000円～3000円高く設定されているところです。\n日・祝日がとてもリーズナブルな値段で泊まることができるだけに、入室時間によっては、他曜日だとかなり割高に感じるところがあります。\n\n別にお気に入りのホテルを見つけたので、今後は利用時間・曜日によって、上手く別のラブホテルと使い分けていきたいです。"
    ]
  },
  {
    "id": "6bb81f2e-a0d4-43ed-b4ac-b208907ba9a7",
    "hotel_name": "ホテル 彩",
    "amenities": [
      "持込用冷蔵庫",
      "電子レンジ",
      "ウォーターサーバー",
      "マッサージチェア※一部",
      "浴室TV",
      "水中照明",
      "ジェット・バブルバス",
      "マット※一部",
      "ウォシュレット",
      "露天風呂※一部",
      "ミストサウナ※一部",
      "ドライサウナ※一部",
      "カラオケ",
      "VOD",
      "Wi-Fi",
      "有線LAN",
      "Android充電器",
      "iPhone充電器",
      "ブルーレイプレーヤー",
      "セレクトシャンプー"
    ],
    "prices": {
      "宿泊": [
        {
          "title": "[日～金・祝日 1部]",
          "price": "8900円～15300円",
          "time": "（ 20:00～翌11:00 の間で最大15時間 ）"
        },
        {
          "title": "[日～金・祝日 2部]",
          "price": "8900円～15300円",
          "time": "（ 23:00～翌05:59 チェックインより12時間 ）"
        },
        {
          "title": "[土・祝前 1部]",
          "price": "10400円～16800円",
          "time": "（ 21:00～翌11:00 の間で最大14時間 ）"
        },
        {
          "title": "[土・祝前 2部]",
          "price": "10400円～16800円",
          "time": "（ 23:00～翌05:59 チェックインより12時間 ）"
        }
      ],
      "休憩": [
        {
          "title": "[月～金]",
          "price": "5900円～9500円",
          "time": "（ 18:00～24:00 滞在時間4時間 ）"
        },
        {
          "title": "[土・日・祝・祝前]",
          "price": "5900円～9500円",
          "time": "（ 18:00～24:00 滞在時間3時間 ）"
        }
      ],
      "サービスタイム": [
        {
          "title": "[月～金・祝前 1部]",
          "price": "5900円～9500円",
          "time": "（ 06:00～09:59 チェックインより8時間 ）"
        },
        {
          "title": "[月～金・祝前 2部]",
          "price": "5900円～9500円",
          "time": "（ 10:00～13:59 チェックインより7時間 ）"
        },
        {
          "title": "[月～金・祝前 3部]",
          "price": "5900円～9500円",
          "time": "（ 14:00～17:59 チェックインより5時間 ）"
        },
        {
          "title": "[土・日・祝 1部]",
          "price": "5900円～9500円",
          "time": "（ 06:00～09:59 チェックインより7時間 ）"
        },
        {
          "title": "[土・日・祝 2部]",
          "price": "5900円～9500円",
          "time": "（ 10:00～13:59 チェックインより5時間 ）"
        },
        {
          "title": "[土・日・祝 3部]",
          "price": "5900円～9500円",
          "time": "（ 14:00～17:59 チェックインより4時間 ）"
        }
      ],
      "延長料金": [
        {
          "title": "[全日]",
          "price": "1300円",
          "time": ""
        }
      ]
    },
    "reviews": [
      "連休前に予約の21時〜11時のプランで利用しました。ネット予約で1時間延長サービスと記載してあったので、予約が完了した後電話で前延長(20時から)でOK貰い、その時間にホテルへ。\n\n到着が少し早かったのでフロントに備え付けの電話で一度聞いたところ、時間まで車でお待ち下さいと。(待合室もちゃんとあり綺麗でした)\n時間になりまた繋いだら部屋の番号を伝えられ、人と会うことなく鍵も必要なくお部屋にチェックイン。入り口の所に自動精算機があり、そこで入退室の手続きをするタイプでした。\n\n泊まったのは一番ランクの低いAランクのお部屋でしたが、それでも広く、アメニティも充実していました。中でもデリケートゾーン用のソープと、トイレにパンティライナーも置いてあったのがすごいなと思いました。テーブル下の箱には爪切りとやすり?も入っていたのでうっかり伸ばしっぱなしにして来てしまった人も整えられます。\nお部屋に電マがあったり、コート掛けの下にある販売機には別のオモチャも入っていたりするので、そういうのを嫌がりそうな女子と来るときは注意が必要かもしれません。\n\nお風呂がウリのホテルで、テレビとBGMのオプションが利用できました。安いお部屋だったので浴槽は２人で入ると手狭でしたが、ランクの高いお部屋ならもっと楽しめると思います。お風呂のアメニティでボディ用のスポンジとネットと２種類あったのも良かったです。\n\nバスローブは紐で結ぶタイプとボタンで閉めるタイプが２つずつ用意してありました。ホテルのロゴ入りでしっかりした長さがあります。タオルはバスタオルとハンドタオルが1人1つずつ+バスマットでした。\n\n給水機はお湯も対応しているもので、ポット要らずでサービスの紅茶などが利用できるのは素敵でした。コーヒーは、カプセル型のコーヒーマシンで楽しめます。\n\n照明パネルはお好みでオンオフが出来る他、プリセットでいくつかボタンが用意されているので、手軽に雰囲気を変えることができます。レインボー照明もお好みで楽しめます。\n\nホテルは拘りがないので何処でも良いのですが、茨城で手軽にカップルズ予約できるところがあまり無いので、また利用するかなと思います。",
      "予約して行った際の料金確認をしたのですが、\n窓口もあまりわかっていなかったのか予約時と\n違う値段を請求されました。間違いに気付いてくれたのは\n良かったのですが、その時の対応がちょっと気になりました。\n最低限、申し訳ございませんの一言は欲しかったです。\n【あー。間違えましたー。】と言われたのは残念です。"
    ]
  },
  {
    "id": "ba9e70d8-7a39-42c6-8903-dcf2697ebe3c",
    "hotel_name": "SALA",
    "amenities": [
      "持込用冷蔵庫",
      "電子レンジ",
      "電気ポット",
      "加湿器",
      "空気清浄機",
      "浴室TV※一部",
      "水中照明",
      "ジェット・バブルバス",
      "ウォシュレット",
      "カラオケ",
      "VOD",
      "TVゲーム※一部",
      "Wi-Fi",
      "有線LAN",
      "Android充電器",
      "iPhone充電器",
      "DVDプレーヤー",
      "ブルーレイプレーヤー※一部",
      "セレクトシャンプー",
      "カールドライヤー"
    ],
    "prices": {
      "宿泊": [
        {
          "title": "[日～木・祝 1部]",
          "price": "7500円～13500円",
          "time": "（ 19:00～翌15:00 最大20時間 ）"
        },
        {
          "title": "[日～木 祝 2部]",
          "price": "5620円～10500円",
          "time": "（ 00:00～17:00 最大17時間 ）"
        },
        {
          "title": "[日～金曜日 早割宿泊]",
          "price": "5620円～11500円",
          "time": "（ 15:00～15:00 ※19時までの入室で最大24時間 ）"
        },
        {
          "title": "[金曜 1部]",
          "price": "7500円～14600円",
          "time": "（ 19:00～翌15:00 最大20時間 ）"
        },
        {
          "title": "[金曜 2部]",
          "price": "7500円～14600円",
          "time": "（ 22:00～翌17:00 最大19時間 ）"
        },
        {
          "title": "[土・特日 1部]",
          "price": "8800円～18700円",
          "time": "（ 15:00～翌12:00 最大21時間 ）"
        },
        {
          "title": "[土・特日 2部]",
          "price": "8800円～16300円",
          "time": "（ 23:00～翌05:00 チェックインより 13時間 ）"
        }
      ],
      "休憩": [
        {
          "title": "[月～木曜（ショート）]",
          "price": "3500円～4400円",
          "time": "（ 05:00～翌04:59 チェックインより 2時間ご利用 ）"
        },
        {
          "title": "[金曜（ショート）]",
          "price": "3500円～4400円",
          "time": "（ 05:00～翌00:59 チェックインより 2時間ご利用 ）"
        },
        {
          "title": "[土・日（ショート）]",
          "price": "3500円～5900円",
          "time": "（ 05:00～翌04:59 チェックインより 2時間ご利用 ）"
        },
        {
          "title": "[月～木 1部]",
          "price": "4900円～8500円",
          "time": "（ 05:00～10:00 チェックインより12時間ご利用 ）"
        },
        {
          "title": "[月～木 2部]",
          "price": "4900円～8500円",
          "time": "（ 10:00～15:00 チェックインより10時間ご利用 ）"
        },
        {
          "title": "[月～木 3部]",
          "price": "4900円～8500円",
          "time": "（ 15:00～18:00 チェックインより9時間ご利用 ）"
        },
        {
          "title": "[月～木 4部]",
          "price": "4900円～8500円",
          "time": "（ 18:30～翌03:00 最大6時間ご利用 ）"
        },
        {
          "title": "[金曜 1部]",
          "price": "4900円～8500円",
          "time": "（ 05:00～10:00 チェックインより 12時間ご利用 ）"
        },
        {
          "title": "[金曜 2部]",
          "price": "4900円～8500円",
          "time": "（ 10:00～15:00 チェックインより 10時間ご利用 ）"
        },
        {
          "title": "[金曜 3部]",
          "price": "4900円～8500円",
          "time": "（ 15:00～18:00 チェックインより 9時間ご利用 ）"
        },
        {
          "title": "[金曜 4部]",
          "price": "5600円～9100円",
          "time": "（ 18:00～翌03:00 最大 6時間ご利用 ）"
        },
        {
          "title": "[土曜・特日 1部]",
          "price": "5600円～9100円",
          "time": "（ 05:00～10:00 チェックインより 12時間ご利用 ）"
        },
        {
          "title": "[土曜・特日 2部]",
          "price": "5600円～9100円",
          "time": "（ 10:00～15:00 チェックインより 10時間ご利用 ）"
        },
        {
          "title": "[土曜・特日 3部]",
          "price": "5600円～9100円",
          "time": "（ 15:00～18:00 チェックインより 9時間ご利用 ）"
        },
        {
          "title": "[土曜・特日 4部]",
          "price": "5600円～9100円",
          "time": "（ 18:00～翌03:00 最大 6時間ご利用 ）"
        },
        {
          "title": "[日曜・祝日 1部]",
          "price": "5600円～9100円",
          "time": "（ 05:00～10:00 チェックインより 10時間ご利用 ）"
        },
        {
          "title": "[日曜・祝日 2部]",
          "price": "5600円～9100円",
          "time": "（ 10:00～15:00 チェックインより 8時間ご利用 ）"
        },
        {
          "title": "[日曜・祝日 3部]",
          "price": "5600円～9100円",
          "time": "（ 15:00～18:00 チェックインより 7時間ご利用 ）"
        },
        {
          "title": "[日曜・祝日 4部]",
          "price": "5600円～9100円",
          "time": "（ 18:00～翌03:00 最大 6時間ご利用 ）"
        }
      ],
      "延長料金": [
        {
          "title": "[月～金]",
          "price": "300円",
          "time": ""
        },
        {
          "title": "[土・日・祝]",
          "price": "400円",
          "time": ""
        }
      ]
    },
    "reviews": [
      "いつも利用させてもらっています。お部屋も綺麗でお風呂も大きくて満足してます。ずっと、飲み放題と夕朝食付きのプランで予約してました。飲み物の提供時間がとてもよく、食事も全て美味しくてお気に入りでした！残念ですが2月からしばらくそのプランが無くなってしまうようで寂しかったです。プランが復活することを祈ってます",
      "フロントの方、女性年配、対応悪すぎました。入る前からとても気分悪く、注文したアメニティーも間違ったものを渡すなど対応最悪。ずっと気分悪かった。また来たいとは当然思えませんでした。料金価格も説明不足でよくわからず、とても高く、予約してたので残念でしたもぉ来ません。"
    ]
  },
  {
    "id": "7a3e7070-a49a-4212-bcb6-b425ec2c09ad",
    "hotel_name": "ホテル ラブ ジュエル 小倉",
    "amenities": [
      "持込用冷蔵庫",
      "電子レンジ",
      "電気ポット",
      "水中照明",
      "ジェット・バブルバス",
      "マット※一部",
      "ウォシュレット",
      "露天風呂※一部",
      "岩盤浴※一部",
      "ドライサウナ※一部",
      "カラオケ※一部",
      "VOD",
      "Wi-Fi",
      "Android充電器",
      "iPhone充電器",
      "DVDプレーヤー※一部",
      "ブルーレイプレーヤー※一部",
      "セレクトシャンプー",
      "ヘアアイロン",
      "電気マッサージ器"
    ],
    "prices": {
      "宿泊": [
        {
          "title": "[月曜日～木曜日　1部]",
          "price": "4750円～10420円",
          "time": "（ 17:00～翌12:00 最長19時間 ）"
        },
        {
          "title": "[月曜日～木曜日　2部]",
          "price": "4750円～10420円",
          "time": "（ 23:00～翌17:00 最長18時間 ）"
        },
        {
          "title": "[金曜日　1部]",
          "price": "7020円～11550円",
          "time": "（ 17:00～翌11:00 最長18時間 ）"
        },
        {
          "title": "[金曜日　2部]",
          "price": "7020円～11550円",
          "time": "（ 00:00～12:00 最長12時間 ）"
        },
        {
          "title": "[土曜日・祝前日　1部]",
          "price": "10420円～15910円",
          "time": "（ 17:00～翌11:00 最長18時間 ）"
        },
        {
          "title": "[土曜日・祝前日　2部]",
          "price": "10420円～15910円",
          "time": "（ 00:00～12:00 最長12時間 ）"
        },
        {
          "title": "[日曜日・祝日　1部]",
          "price": "5880円～9850円",
          "time": "（ 17:00～翌12:00 最長19時間 ）"
        },
        {
          "title": "[日曜日・祝日 2部]",
          "price": "5880円～9850円",
          "time": "（ 23:00～翌17:00 最長18時間 ）"
        }
      ],
      "休憩": [
        {
          "title": "[ショートタイム　月曜日～金曜日]",
          "price": "2490円～5880円",
          "time": "（ 04:00～24:00 滞在時間2時間 ）"
        },
        {
          "title": "[ショートタイム土曜日・日曜日・祝日]",
          "price": "4750円～7020円",
          "time": "（ 04:00～24:00 滞在時間2時間 ）"
        },
        {
          "title": "[月曜日～金曜日]",
          "price": "3620円～6450円",
          "time": "（ 04:00～24:00 滞在時間4時間 ）"
        },
        {
          "title": "[土曜日・日曜日・祝日]",
          "price": "5430円～7580円",
          "time": "（ 04:00～24:00 滞在時間4時間 ）"
        }
      ],
      "サービスタイム": [
        {
          "title": "[月曜日～金曜日　]",
          "price": "3840円～7580円",
          "time": "（ 04:00～22:00 最長18時間 ）"
        },
        {
          "title": "[土曜日・日曜日・祝日]",
          "price": "5880円～8720円",
          "time": "（ 04:00～19:00 最長15時間 ）"
        }
      ],
      "延長料金": [
        {
          "title": "[全日]",
          "price": "1240円",
          "time": ""
        }
      ]
    },
    "reviews": [
      "先日利用させて頂きましたが、飲み放題で歌い放題♪\nこんなホテルがあるなんて正直驚きました！\n接客もすごく丁寧で感激しました。\n他にも色んな部屋があるみたいで、是非また寄らせてもらいます！",
      "忙しいであろう年末でも本当に親切､丁寧､\n柔軟な対応をしてくださるスタッフさん\n掃除も行き届いている室内\nそして値段以上のお味のモーニング\nこの料金でこのサービスには驚きました！！\nぜひまた利用したいホテルです。"
    ]
  },
  {
    "id": "075a9493-c22c-41f9-9d9f-c86e5936c6de",
    "hotel_name": "HOTEL ZEN 港北",
    "amenities": [
      "持込用冷蔵庫",
      "電子レンジ",
      "電気ポット",
      "加湿器",
      "空気清浄機",
      "マッサージチェア※一部",
      "浴室TV",
      "水中照明",
      "ジェット・バブルバス",
      "ウォシュレット",
      "露天風呂※一部",
      "岩盤浴※一部",
      "ドライサウナ※一部",
      "VOD",
      "TVゲーム",
      "Wi-Fi",
      "有線LAN",
      "Android充電器",
      "iPhone充電器",
      "ブルーレイプレーヤー"
    ],
    "prices": {
      "宿泊": [
        {
          "title": "[日～木・祝1部]",
          "price": "8500円～18900円",
          "time": "（ 18:00～翌12:00 ）"
        },
        {
          "title": "[日～木・祝2部]",
          "price": "8500円～18900円",
          "time": "（ 00:00～14:00 ）"
        },
        {
          "title": "[金曜1部]",
          "price": "9600円～20000円",
          "time": "（ 18:00～翌12:00 ）"
        },
        {
          "title": "[金曜2部]",
          "price": "9600円～20000円",
          "time": "（ 00:00～14:00 ）"
        },
        {
          "title": "[土・祝前1部]",
          "price": "11800円～22200円",
          "time": "（ 18:00～翌11:00 ）"
        },
        {
          "title": "[土・祝前2部]",
          "price": "11800円～22200円",
          "time": "（ 00:00～13:00 ）"
        }
      ],
      "休憩": [
        {
          "title": "[ショート：月～金]",
          "price": "4500円～8900円",
          "time": "（ 05:00～24:00 滞在時間2時間 ）"
        },
        {
          "title": "[ショート：土・日・祝]",
          "price": "5900円～10300円",
          "time": "（ 05:00～24:00 滞在時間2時間 ）"
        },
        {
          "title": "[月～金]",
          "price": "5500円～9900円",
          "time": "（ 05:00～24:00 滞在時間3時間 ）"
        },
        {
          "title": "[土・日・祝]",
          "price": "6900円～11300円",
          "time": "（ 05:00～24:00 滞在時間3時間 ）"
        }
      ],
      "サービスタイム": [
        {
          "title": "[月～金1部]",
          "price": "5900円～12900円",
          "time": "（ 05:00～09:00 IN 滞在時間10時間 ）"
        },
        {
          "title": "[月～金2部]",
          "price": "5900円～12900円",
          "time": "（ 09:00～14:00 IN 滞在時間8時間 ）"
        },
        {
          "title": "[月～金3部]",
          "price": "5900円～12900円",
          "time": "（ 14:00～18:00 IN 滞在時間6時間 ）"
        },
        {
          "title": "[土・日・祝1部]",
          "price": "7300円～14300円",
          "time": "（ 05:00～09:00 IN 滞在時間8時間 ）"
        },
        {
          "title": "[土・日・祝2部]",
          "price": "7300円～14300円",
          "time": "（ 09:00～14:00 IN 滞在時間6時間 ）"
        },
        {
          "title": "[土・日・祝3部]",
          "price": "7300円～14300円",
          "time": "（ 14:00～18:00 IN 滞在時間4時間 ）"
        }
      ],
      "延長料金": [
        {
          "title": "[月〜金]",
          "price": "1300円～1700円",
          "time": ""
        },
        {
          "title": "[土・日・祝日]",
          "price": "1500円～1900円",
          "time": ""
        }
      ]
    },
    "reviews": [
      "サウナ、露天風呂付きのお部屋に宿泊しました。\n内風呂にお湯を張るとゴミが浮いてくるなど少しだけ気になるところはありましたが、全体的に清潔で広々していて良いです。\n露天風呂も広くて夜の使用が最高でした。\n\nただ、部屋に備え付けのタブレットを見たところ朝食無料とあったので、嬉しいサービスだな〜と思い翌朝頼もうとしたところ時間外(まだ9時代)と表示されてしまいました。フロントに連絡したところ朝5時までの予約制でタブレットではなく冊子に記載されてるとのこと。\n今時冊子で確認する人は少ないと思いますし、みんなTVかタブレットでメニューを確認すると思うので、到着時にフロントでその旨を伝えるのが親切ではないでしょうか。\nしかも、私も確認不足だった部分があったとはいえ、フロントに電話させて頂いたときに一言も「申し訳ございません」がなく、説明の一点張りで電話も先に切られ、態度の悪さにかなり不快に思いました。\nサービス業であれば普通理不尽に思ってもお客様の要望にこたえられない時ひとこと必ず謝るはずです。グループホテルでそのへんはしっかりしていると思っていたのでかなり残念でした。\nサービスの面は見直ししていただきたいのと、お客様目線の親切なチェックインをしていただきたいです。\n彼の誕生日だったので、台無しにされた気分になり非常に残念でした。",
      "大切な人が出来ました！\n朝から逢う約束をして、朝食後利用させて頂きました。HOTELなんてご無沙汰ぶりだっので緊張とワクワクで…w部屋のアレコレに困惑しながらも\n快適に大事な時間が過ごせましたー！！\nまた、利用したいです。"
    ]
  },
  {
    "id": "e44aee73-a8a4-42eb-8eb1-9806638744fd",
    "hotel_name": "HOTEL ZEN RIKYU 横浜町田",
    "amenities": [
      "持込用冷蔵庫",
      "電子レンジ",
      "電気ポット",
      "加湿器",
      "空気清浄機",
      "マッサージチェア※一部",
      "浴室TV",
      "水中照明",
      "ジェット・バブルバス",
      "ウォシュレット",
      "露天風呂※一部",
      "VOD",
      "Wi-Fi",
      "Android充電器",
      "iPhone充電器",
      "ブルーレイプレーヤー",
      "セレクトシャンプー",
      "カールドライヤー",
      "ヘアアイロン",
      "電気マッサージ器"
    ],
    "prices": {
      "宿泊": [
        {
          "title": "[日～木1部]",
          "price": "7900円～16000円",
          "time": "（ 18:00～23:00 までの入室で翌14:00まで ）"
        },
        {
          "title": "[日～木2部]",
          "price": "7900円～16000円",
          "time": "（ 23:00～翌05:00 までの入室で入室から15時間 ）"
        },
        {
          "title": "[金1部]",
          "price": "9000円～17100円",
          "time": "（ 18:00～23:00 までの入室で翌14:00まで ）"
        },
        {
          "title": "[金2部]",
          "price": "9000円～17100円",
          "time": "（ 23:00～翌05:00 までの入室で入室から15時間 ）"
        },
        {
          "title": "[土・祝前・特日1部]",
          "price": "11200円～19300円",
          "time": "（ 18:00～翌11:00 ）"
        },
        {
          "title": "[土・祝前・特日2部]",
          "price": "11200円～19300円",
          "time": "（ 23:00～翌05:00 までの入室で入室から12時間 ）"
        }
      ],
      "休憩": [
        {
          "title": "[【ショート】月～金]",
          "price": "3500円～11000円",
          "time": "（ 05:00～24:00 滞在時間2時間 ）"
        },
        {
          "title": "[【ショート】土・日・祝日]",
          "price": "4800円～12300円",
          "time": "（ 05:00～24:00 滞在時間2時間 ）"
        },
        {
          "title": "[月～金]",
          "price": "4500円～12000円",
          "time": "（ 05:00～24:00 滞在時間4時間 ）"
        },
        {
          "title": "[土・日・祝日]",
          "price": "5800円～13300円",
          "time": "（ 05:00～24:00 滞在時間4時間 ）"
        }
      ],
      "サービスタイム": [
        {
          "title": "[月～金1部]",
          "price": "5500円～13000円",
          "time": "（ 05:00～10:00 IN 滞在時間12時間 ）"
        },
        {
          "title": "[月～金2部]",
          "price": "5500円～13000円",
          "time": "（ 10:00～13:00 IN 滞在時間10時間 ）"
        },
        {
          "title": "[月～金3部]",
          "price": "5500円～13000円",
          "time": "（ 13:00～18:00 IN 滞在時間8時間 ）"
        },
        {
          "title": "[土・日・祝日1部]",
          "price": "6800円～14300円",
          "time": "（ 05:00～10:00 IN 滞在時間10時間 ）"
        },
        {
          "title": "[土・日・祝日2部]",
          "price": "6800円～14300円",
          "time": "（ 10:00～13:00 IN 滞在時間8時間 ）"
        },
        {
          "title": "[土・日・祝日3部]",
          "price": "6800円～14300円",
          "time": "（ 13:00～18:00 IN 滞在時間7時間 ）"
        }
      ],
      "延長料金": [
        {
          "title": "[全日]",
          "price": "1300円～1600円",
          "time": ""
        }
      ]
    },
    "reviews": [
      "今回また利用させてもらいましたが、今度はトイレのウォシュレットが使えませんでした?クレーム入れようかと思いましたが、１日我慢すれば良いので泣く泣く過ごしました。あと国道脇なので、ヤンチャ坊主達のバイクの音が凄かった。",
      "部屋は広く、綺麗でテレビも大きく見やすいので、くつろぐには最高です。\nただ今回初めての出来事なのですが、床がベタベタしている部分がありました。何回も利用させてもらってて初めての事だったのでちょっとショックでした。\nでも、それ以外は申し分ないのでまた利用させていただきます。"
    ]
  },
  {
    "id": "d07ebe9b-1ec7-45ea-9f21-96d258953eb1",
    "hotel_name": "HOTEL ZEN 横浜羽沢",
    "amenities": [
      "持込用冷蔵庫",
      "電子レンジ",
      "電気ポット",
      "加湿器",
      "空気清浄機",
      "マッサージチェア※一部",
      "浴室TV",
      "水中照明",
      "ジェット・バブルバス",
      "ウォシュレット",
      "露天風呂※一部",
      "岩盤浴※一部",
      "ドライサウナ※一部",
      "VOD",
      "TVゲーム",
      "Wi-Fi",
      "有線LAN",
      "Android充電器",
      "iPhone充電器",
      "ブルーレイプレーヤー"
    ],
    "prices": {
      "宿泊": [
        {
          "title": "[日～木・祝1部]",
          "price": "8200円～21000円",
          "time": "（ 18:00～翌12:00 ）"
        },
        {
          "title": "[日～木・祝2部]",
          "price": "8200円～21000円",
          "time": "（ 00:00～15:00 ）"
        },
        {
          "title": "[金曜1部]",
          "price": "9300円～22100円",
          "time": "（ 18:00～翌12:00 ）"
        },
        {
          "title": "[金曜2部]",
          "price": "9300円～22100円",
          "time": "（ 00:00～15:00 ）"
        },
        {
          "title": "[土・祝前1部]",
          "price": "11500円～24254円",
          "time": "（ 18:00～翌11:00 ）"
        },
        {
          "title": "[土・祝前2部]",
          "price": "11500円～24300円",
          "time": "（ 22:00～翌12:00 ）"
        }
      ],
      "休憩": [
        {
          "title": "[ショート：月～金]",
          "price": "4300円～10500円",
          "time": "（ 05:00～24:00 滞在時間2時間 ）"
        },
        {
          "title": "[ショート：土・日・祝]",
          "price": "5700円～11900円",
          "time": "（ 05:00～24:00 滞在時間2時間 ）"
        },
        {
          "title": "[月～金]",
          "price": "5500円～11500円",
          "time": "（ 05:00～24:00 滞在時間3時間 ）"
        },
        {
          "title": "[土・日・祝]",
          "price": "6900円～12900円",
          "time": "（ 05:00～24:00 滞在時間3時間 ）"
        }
      ],
      "サービスタイム": [
        {
          "title": "[月～金1部]",
          "price": "5900円～12500円",
          "time": "（ 05:00～09:00 IN 滞在時間10時間 ）"
        },
        {
          "title": "[月～金2部]",
          "price": "5900円～12465円",
          "time": "（ 09:00～14:00 IN 滞在時間8時間 ）"
        },
        {
          "title": "[月～金3部]",
          "price": "5900円～12500円",
          "time": "（ 14:00～18:00 IN 滞在時間6時間 ）"
        },
        {
          "title": "[土・日・祝1部]",
          "price": "7300円～13900円",
          "time": "（ 05:00～09:00 IN 滞在時間8時間 ）"
        },
        {
          "title": "[土・日・祝2部]",
          "price": "7300円～13873円",
          "time": "（ 09:00～14:00 IN 滞在時間6時間 ）"
        },
        {
          "title": "[土・日・祝3部]",
          "price": "7300円～13900円",
          "time": "（ 14:00～18:00 IN 滞在時間4時間 ）"
        }
      ],
      "延長料金": [
        {
          "title": "[月〜金]",
          "price": "1300円～2000円",
          "time": ""
        },
        {
          "title": "[土・日・祝日]",
          "price": "1500円～2171円",
          "time": ""
        }
      ]
    },
    "reviews": [
      "まず入って気づいたのが、テレビの位置が微妙。\nソファからは真正面だからOKだけど、ベッドからは全然ダメ。\nテレビとベッドの向きが同じって変ですよ？\nそして最悪なのがいざ寝ようと思ったら、ボイラーの作動音がうるさくて眠れない。\nこれがホントにひどくて、ずーっと、一定の音量・音質で騒いでいるならまだ我慢できるが、\n断続的に作動するので、音量・音質が安定しないから、気になって眠れない。実際寝てませんから！！",
      "価格が消費税別、支払う時に気がついた\n金額とか時間の事とか部屋のインフォメーションにも載ってないから分かりづらかった\nオープンしたばっかりだから部屋はキレイで凄く良い\n精算機の前で他のお客さんと会うのが少しイヤかな"
    ]
  },
  {
    "id": "9abe148a-ed1b-47ef-aade-6eb279476cd0",
    "hotel_name": "Will Base 鶴見",
    "amenities": [
      "持込用冷蔵庫",
      "電子レンジ",
      "電気ポット",
      "ウォーターサーバー",
      "加湿器",
      "空気清浄機",
      "浴室TV",
      "水中照明",
      "ジェット・バブルバス",
      "ウォシュレット",
      "カラオケ※一部",
      "VOD",
      "Wi-Fi",
      "有線LAN",
      "Android充電器",
      "iPhone充電器",
      "DVDプレーヤー",
      "ブルーレイプレーヤー",
      "クロームキャスト",
      "セレクトシャンプー"
    ],
    "prices": {
      "宿泊": [
        {
          "title": "[日～木・祝1部]",
          "price": "8800円～11500円",
          "time": "（ 18:00～翌12:00 最大18時間 ）"
        },
        {
          "title": "[日～木・祝2部]",
          "price": "8800円～11500円",
          "time": "（ 22:00～翌15:00 最大17時間 ）"
        },
        {
          "title": "[【ロングステイ】日～木・祝]",
          "price": "12500円～16000円",
          "time": "（ 15:00～翌12:00 最大21時間 ）"
        },
        {
          "title": "[金曜日]",
          "price": "9300円～12000円",
          "time": "（ 21:00～翌12:00 最大15時間 ）"
        },
        {
          "title": "[【ロングステイ】金曜日]",
          "price": "13000円～16500円",
          "time": "（ 15:00～翌12:00 最大21時間 ）"
        },
        {
          "title": "[土・祝前・特日]",
          "price": "10300円～13000円",
          "time": "（ 21:00～翌11:00 最大14時間 ）"
        },
        {
          "title": "[【ロングステイ】土・祝前・特日]",
          "price": "15900円～19900円",
          "time": "（ 15:00～翌11:00 最大20時間 ）"
        }
      ],
      "休憩": [
        {
          "title": "[月～金・祝前（ショート）]",
          "price": "4200円～5800円",
          "time": "（ 05:00～22:00 まで入室可 滞在時間2時間 ）"
        },
        {
          "title": "[月～金・祝前]",
          "price": "5300円～6900円",
          "time": "（ 05:00～翌02:00 の間 滞在時間4時間 ）"
        },
        {
          "title": "[土・日・祝日・特日（ショート）]",
          "price": "4800円～6300円",
          "time": "（ 05:00～22:00 の間 滞在時間2時間 ）"
        },
        {
          "title": "[土・日・祝日・特日]",
          "price": "5800円～7500円",
          "time": "（ 05:00～翌02:00 の間 滞在時間3時間 ）"
        }
      ],
      "サービスタイム": [
        {
          "title": "[月～金・祝前1部]",
          "price": "5800円～7400円",
          "time": "（ 05:00～18:00 滞在時間13時間 ）"
        },
        {
          "title": "[月～金・祝前2部]",
          "price": "5800円～7400円",
          "time": "（ 12:00～20:00 滞在時間8時間 ）"
        },
        {
          "title": "[月～金・祝前3部]",
          "price": "5800円～7400円",
          "time": "（ 15:00～23:00 滞在時間8時間 ）"
        },
        {
          "title": "[土・日・祝日・特日1部]",
          "price": "6300円～7900円",
          "time": "（ 05:00～16:00 滞在時間11時間 ）"
        },
        {
          "title": "[土・日・祝日・特日2部]",
          "price": "6300円～7900円",
          "time": "（ 12:00～19:00 滞在時間7時間 ）"
        }
      ],
      "延長料金": [
        {
          "title": "[全日]",
          "price": "700円",
          "time": ""
        }
      ]
    },
    "reviews": [
      "ロビーは落ち着いた感じでドリンクの種類やアメニティ－も沢山で嬉しい、フロントは女性でとても親切でした。お部屋にはコーヒーメーカーがあり自分で作れて好きな時に飲めるのがいいです。\nお風呂にはスチームサウナもあって浴槽も広くゆっくりできました。また、利用させて頂きます。"
    ]
  },
  {
    "id": "680add16-c7c8-4547-9fde-fd1e4d6d0432",
    "hotel_name": "HOTEL LIBERTY",
    "amenities": [],
    "prices": {},
    "reviews": []
  },
  {
    "id": "275df24d-1d93-4c73-bf7c-1d52ed2be761",
    "hotel_name": "ホテル サル・デ・バーン",
    "amenities": [
      "持込用冷蔵庫",
      "電子レンジ",
      "電気ポット※一部",
      "ウォーターサーバー",
      "加湿器※一部",
      "空気清浄機",
      "浴室TV",
      "ジェット・バブルバス※一部",
      "ウォシュレット",
      "VOD",
      "Wi-Fi",
      "Android充電器",
      "iPhone充電器",
      "DVDプレーヤー",
      "ブルーレイプレーヤー※一部",
      "セレクトシャンプー",
      "カールドライヤー",
      "ヘアアイロン",
      "コスプレ",
      "和室※一部"
    ],
    "prices": {
      "宿泊": [
        {
          "title": "[日〜木]",
          "price": "8330円～11430円",
          "time": "（ 21:00～翌12:00 INより15h ）"
        },
        {
          "title": "[金曜]",
          "price": "11830円～14430円",
          "time": "（ 21:00～翌12:00 INより15h ）"
        },
        {
          "title": "[土・祝前]",
          "price": "12530円～14730円",
          "time": "（ 22:00～翌12:00 INより14h ）"
        }
      ],
      "休憩": [
        {
          "title": "[月～金 60分]",
          "price": "4930円～7630円",
          "time": "（ 06:00～24:00 INより60分 ）"
        },
        {
          "title": "[月～金 90分]",
          "price": "4930円～8180円",
          "time": "（ 06:00～24:00 INより90分 ）"
        },
        {
          "title": "[土・日・祝 60分]",
          "price": "6030円～8230円",
          "time": "（ 06:00～24:00 INより60分 ）"
        },
        {
          "title": "[土・日・祝 90分]",
          "price": "6580円～8980円",
          "time": "（ 06:00～24:00 INより90分 ）"
        }
      ],
      "サービスタイム": [
        {
          "title": "[月～金]",
          "price": "7980円～10180円",
          "time": "（ 06:00～20:00 最大14h ）"
        },
        {
          "title": "[土・日・祝]",
          "price": "8980円～11680円",
          "time": "（ 06:00～18:00 最大12h ）"
        }
      ],
      "延長料金": [
        {
          "title": "[全日]",
          "price": "1000円",
          "time": ""
        }
      ]
    },
    "reviews": [
      "良い点は有るが、悪い点が勝ったかな。\n\n良い点\n・電話予約した際や受付での対応は良かった。\n・部屋にウォーターサーバーがある。\n\n悪い点\n・無料Wi-Fiが繋がらない。正確に言うとネットワーク名やパスワードの記載はあるがスマホ側に表示されず、検索をかけてもヒットしないので繋げようがない。\n・部屋に対して値段が高いように感じる。",
      "クーポンを提示しましたが\n帰りの請求額はクーポンより高かったです\n\nフロントの方も感じ悪かったです"
    ]
  },
  {
    "id": "2768a94a-3187-45e8-9d13-01493d7c78b0",
    "hotel_name": "ホテル パシオンリゾート",
    "amenities": [
      "持込用冷蔵庫",
      "電子レンジ",
      "電気ポット",
      "加湿器",
      "空気清浄機",
      "マッサージチェア※一部",
      "お姫様(天蓋)ベッド※一部",
      "水中照明",
      "ジェット・バブルバス",
      "ウォシュレット",
      "Wi-Fi",
      "有線LAN",
      "Android充電器※一部",
      "iPhone充電器",
      "ブルーレイプレーヤー※一部",
      "セレクトシャンプー※一部",
      "カールドライヤー",
      "ヘアアイロン※一部",
      "電気マッサージ器",
      "コスプレ※一部"
    ],
    "prices": {
      "宿泊": [
        {
          "title": "[日～木・祝 1部]",
          "price": "7000円～10500円",
          "time": "（ 19:00～翌12:00 の間で最大17時間 ）"
        },
        {
          "title": "[日～木・祝 2部]",
          "price": "7000円～10500円",
          "time": "（ 00:00～15:00 の間で最大15時間 ）"
        },
        {
          "title": "[金 1部]",
          "price": "8000円～11500円",
          "time": "（ 21:00～翌11:00 の間で最大14時間 ）"
        },
        {
          "title": "[金 2部]",
          "price": "8000円～11500円",
          "time": "（ 00:00～13:00 の間で最大13時間 ）"
        },
        {
          "title": "[土・祝前 1部]",
          "price": "11500円～16000円",
          "time": "（ 21:00～翌11:00 の間で最大14時間 ）"
        },
        {
          "title": "[土・祝前 2部]",
          "price": "11500円～16000円",
          "time": "（ 00:00～13:00 の間で最大13時間 ）"
        }
      ],
      "休憩": [
        {
          "title": "[全日【ショートタイム】※A～Dタイプのみ]",
          "price": "3800円～4500円",
          "time": "（ 06:00～24:00 の間で最大2時間 ）"
        },
        {
          "title": "[月～金【A～Eランク】]",
          "price": "4500円～6000円",
          "time": "（ 06:00～24:00 の間で最大4時間 ）"
        },
        {
          "title": "[月～金【F・Gランク】]",
          "price": "6500円～7000円",
          "time": "（ 06:00～24:00 の間で最大5時間 ）"
        },
        {
          "title": "[土・日・祝【A～Eランク】]",
          "price": "5000円～6500円",
          "time": "（ 06:00～24:00 の間で最大4時間 ）"
        },
        {
          "title": "[土・日・祝【F・Gランク】]",
          "price": "7000円～7500円",
          "time": "（ 06:00～24:00 の間で最大5時間 ）"
        }
      ],
      "サービスタイム": [
        {
          "title": "[月～金 1部]",
          "price": "4500円～7000円",
          "time": "（ 06:00～17:00 の間で最大11時間 ）"
        },
        {
          "title": "[月～金 2部]",
          "price": "4500円～7000円",
          "time": "（ 13:00～21:00 の間で最大8時間 ）"
        },
        {
          "title": "[土・日・祝]",
          "price": "5000円～7500円",
          "time": "（ 06:00～17:00 の間で最大8時間 ）"
        }
      ],
      "延長料金": [
        {
          "title": "[全日]",
          "price": "1500円",
          "time": ""
        }
      ]
    },
    "reviews": []
  },
  {
    "id": "7117f616-8f9a-4f30-add7-969973280568",
    "hotel_name": "HOTEL HEAVEN",
    "amenities": [
      "持込用冷蔵庫",
      "電子レンジ※一部",
      "電気ポット",
      "空気清浄機",
      "お姫様(天蓋)ベッド※一部",
      "水中照明※一部",
      "ジェット・バブルバス※一部",
      "ウォシュレット※一部",
      "カラオケ",
      "VOD",
      "TVゲーム※一部",
      "Wi-Fi",
      "Android充電器※一部",
      "iPhone充電器※一部",
      "セレクトシャンプー※一部",
      "カールドライヤー※一部",
      "ヘアアイロン※一部",
      "バスローブ",
      "3名以上利用可",
      "1名利用可"
    ],
    "prices": {
      "宿泊": [
        {
          "title": "[日～金]",
          "price": "7500円～10000円",
          "time": "（ 20:00～翌11:00 の間で最大15時間 ）"
        },
        {
          "title": "[土・祝前]",
          "price": "8000円～10500円",
          "time": "（ 22:00～翌11:00 の間で最大13時間 ）"
        }
      ],
      "休憩": [
        {
          "title": "[平日]",
          "price": "4500円～6000円",
          "time": "（ 16:00～24:00 の間で3時間 ）"
        },
        {
          "title": "[土・日・祝]",
          "price": "5000円～6500円",
          "time": "（ 16:00～24:00 チェックインより3時間 ）"
        }
      ],
      "フリータイム": [
        {
          "title": "[月～金]",
          "price": "4500円",
          "time": "（ 05:00～16:00 の間で最大11時間 ）"
        },
        {
          "title": "[土・日・祝]",
          "price": "5000円",
          "time": "（ 05:00～16:00 の間で最大11時間 ）"
        }
      ],
      "延長料金": [
        {
          "title": "[全日]",
          "price": "1000円",
          "time": ""
        }
      ]
    },
    "reviews": [
      "とても雰囲気良くて良かったと思います。年末価格っていうのもあり、多少高めでしたが、普段がどのくらいなのか気になりますね",
      "まず部屋の壁紙が剥がれてる所が何ヵ所もあるしコンセントもベッドから遠いところにあり不便。\nベッドも寝返り打ったらきしむ音がする。\nお風呂もシャワーヘッドの繋ぎ目から水が漏れてる。\nジャグジーの水貯める際も蛇口が3つありどれがお湯なのかの調整する蛇口かわからないし、ジャグジーに付いてるシャワーヘッドから水漏れする。\n洗面台のスイッチも調整するのがなく0かq00%の明るさしかない\nベッド周辺の証明も調整するのがあるが0か100しか調整できない\nテレビもノイズがひどいし部屋でカラオケ出来るが本で検索するタイプで冊子が2020年が最新だった\nもう利用することはない"
    ]
  },
  {
    "id": "dab4e42d-595d-4a38-9af5-5e8187057262",
    "hotel_name": "HOTEL GRAND CHARIOT",
    "amenities": [],
    "prices": {},
    "reviews": [
      "空気清浄機がタバコ臭く、運転を中止した方がマシ。部屋中リセッシュしたが、持参したパジャマや服がヤニ臭くなった。恐らく空調のせいだろう。部屋のインテリアは美しく、マッサージチェアもお気に入りのブランドだった。ドライサウナも気に入った。バスタオルはガサガサで触るに耐えない。値段は相場並。",
      "サービスタイムで最上階に行きました。\n内装は素晴らしいの一言で皆さん満足できるかと思います。ただ素晴らしい分値段は張りますが。"
    ]
  },
  {
    "id": "3e061336-eb20-4909-b473-b4adaf5cd5ae",
    "hotel_name": "Hotel  Eastern (ホテル イースタン)",
    "amenities": [],
    "prices": {},
    "reviews": [
      "サービスタイムの時間の長さの割に安くて良かったです!\n清潔感もあり、接客も丁寧。\nお風呂も広かったので大満足です。また利用したいです。",
      "料金や滞在時間は魅力的^^\nここに泊まって料金=部屋の質だと思いました(><)\n\nせめて冷蔵庫くらいは用意してて欲しかったです(;;`)"
    ]
  },
  {
    "id": "4dcbc035-3a90-493f-8114-77a49810fd6a",
    "hotel_name": "HOTEL SENSE 東京",
    "amenities": [],
    "prices": {},
    "reviews": [
      "タイムサービスだったのか、休憩で5000円でした！\n安い！\n\n階段降りて受付へ。ここの雰囲気がいいですね。\n階段上がるのはつらいですが(笑)\n\n満室だったので、待っているところへ。\n待合室?がすごくいい感じでした。\nエントランスに水槽もあり、癒されました～\n\nカジュアルですかね？ラグジュアリーという感じではなかったです～",
      "露天は湯船専用蛇口からあまり熱いお湯が出なかったのでシャワーを1番熱くしてお湯溜め。\n追い炊きないので湯冷め注意\n水圧弱めも難点\n大きめTVやライトアップ、ベンチは◎\n部屋のTVも機能が充実\nご飯も美味！\nペンネグラタンがオススメ\nベッドも枕も最高\n暖房も業務用？の大きいやつでよく利きました\n是非通いたいです♪\nただTVと露天の操作が難しかった\n露天は何の記載もないボタンが多くて…\nラベル等貼って頂けたら助かります"
    ]
  },
  {
    "id": "55139bf8-8715-49cf-a384-b6b6f7986285",
    "hotel_name": "HOTEL  ペガサス",
    "amenities": [],
    "prices": {},
    "reviews": [
      "１６時ごろに利用しましたが、すでに部屋はほとんど埋まってて、場所柄かなと。\n料金は５７００円となりました。次回利用できる割引券５００円をもらいましたが、来月末までというには５００円は安すぎるかな。\n部屋の入り口がちょっと狭いけど、中に入るとダブルベッドどーんとあって、広々。\nシャワーがちょっと温度調整難しかったけど、勢いもよくてGOOD。\n特にタバコ臭くもなく、隣の部屋の声が聞こえることもなく、大変満足でした。"
    ]
  },
  {
    "id": "1d8cc10b-01f6-4f24-94d3-081658b32594",
    "hotel_name": "Hotel Mitsuru (ホテル ミツル)",
    "amenities": [],
    "prices": {},
    "reviews": []
  },
  {
    "id": "d70ad9cd-7bd3-48e3-8b97-0975a9ee13ab",
    "hotel_name": "ホテル ベネチアン",
    "amenities": [],
    "prices": {},
    "reviews": []
  },
  {
    "id": "424b8666-d00c-4e34-8eff-b62aece205a0",
    "hotel_name": "HOTEL SK PLAZA (ホテル エスケープラザ)",
    "amenities": [],
    "prices": {},
    "reviews": []
  },
  {
    "id": "fd9d59d8-e3ae-4ea6-a335-7c3092e1e191",
    "hotel_name": "HOTEL 1.10.1 (ホテル ワンテンワン)",
    "amenities": [],
    "prices": {},
    "reviews": [
      "JR恵比寿駅から近いため利用。\n2時間9,400円の値段の割に、お水は1本のみという有り得なさに驚愕。\n部屋は6～8畳程度で、ベッドはマットレスのみのような低さに加え、低すぎる＆狭すぎるソファ。\nさすがにトイレとシャワールームは分かれてい。\nしかし、シャワールームは出入口側に近く、ベッドとは扉で仕切ることができる。\nつまり、シャワーを浴びるテイで出入口から逃げることができる。（エントランスで止められるだろうが）\nいろいろ不満要素があるため、もう利用しない。"
    ]
  },
  {
    "id": "aeda569a-7bde-4465-8a4e-8aea81e36199",
    "hotel_name": "HOTEL  SCHALL (シャール)",
    "amenities": [],
    "prices": {},
    "reviews": []
  },
  {
    "id": "c6d1b4ec-9ed7-46be-a44f-924c1c99e2bf",
    "hotel_name": "HOTEL sugar (ホテル シュガー)",
    "amenities": [],
    "prices": {},
    "reviews": []
  },
  {
    "id": "abb8e307-27b6-4f84-aa4a-09bdd9027f59",
    "hotel_name": "HOTEL FAVUER (ホテル ファヴール)",
    "amenities": [],
    "prices": {},
    "reviews": []
  },
  {
    "id": "665f1675-bf64-4435-94e5-d40b385ed2ef",
    "hotel_name": "HOTEL AREAS 渋谷 (エリアス渋谷)",
    "amenities": [],
    "prices": {},
    "reviews": [
      "初めての利用でしたが、部屋は広く清潔でした。\n紙コップは少し味気ないですね。"
    ]
  },
  {
    "id": "94109eb4-88a4-4179-88c1-4afd5f01eb11",
    "hotel_name": "Bali Thai Hotel&Resort 福生店 (バリタイホテル アンドリゾート福生店)",
    "amenities": [],
    "prices": {},
    "reviews": []
  },
  {
    "id": "c8316182-42ba-41c7-bf00-3c17b58e4988",
    "hotel_name": "HOTEL Monbijou (ホテル モンビジュ)",
    "amenities": [],
    "prices": {},
    "reviews": []
  },
  {
    "id": "19b20547-7377-4ee5-9704-9068edaf801a",
    "hotel_name": "HOTEL AZ（ホテル アズ）",
    "amenities": [
      "持込用冷蔵庫",
      "電子レンジ",
      "電気ポット",
      "加湿器※一部",
      "空気清浄機",
      "マッサージチェア※一部",
      "浴室TV",
      "ジェット・バブルバス",
      "ウォシュレット",
      "ドライサウナ※一部",
      "VOD",
      "Wi-Fi",
      "Android充電器※一部",
      "iPhone充電器※一部",
      "DVDプレーヤー",
      "ブルーレイプレーヤー",
      "カールドライヤー",
      "ヘアアイロン",
      "バスローブ",
      "ルームサービス"
    ],
    "prices": {
      "宿泊": [
        {
          "title": "[日～木・祝1部]",
          "price": "10300円～14000円",
          "time": "（ 20:00～翌12:00 最大16時間 ）"
        },
        {
          "title": "[日～木・祝2部]",
          "price": "10300円～14000円",
          "time": "（ 01:00～05:00 チェックインより11時間 ）"
        },
        {
          "title": "[金1部]",
          "price": "11400円～15100円",
          "time": "（ 20:00～翌10:00 最大14時間 ）"
        },
        {
          "title": "[金2部]",
          "price": "11400円～15100円",
          "time": "（ 01:00～12:00 最大11時間 ）"
        },
        {
          "title": "[土・祝前1部]",
          "price": "13600円～17300円",
          "time": "（ 22:00～翌10:00 最大12時間 ）"
        },
        {
          "title": "[土・祝前2部]",
          "price": "13600円～17300円",
          "time": "（ 01:00～12:00 最大11時間 ）"
        }
      ],
      "休憩": [
        {
          "title": "[全日]",
          "price": "6500円～8800円",
          "time": "（ 05:00～24:00 滞在時間3時間 ）"
        }
      ],
      "サービスタイム": [
        {
          "title": "[月～金1部]",
          "price": "6500円～8800円",
          "time": "（ 05:00～15:00 滞在時間10時間 ）"
        },
        {
          "title": "[月～金2部]",
          "price": "6500円～8800円",
          "time": "（ 09:00～18:00 滞在時間9時間 ）"
        },
        {
          "title": "[月～金3部]",
          "price": "6500円～8800円",
          "time": "（ 13:00～20:00 滞在時間7時間 ）"
        },
        {
          "title": "[土・日・祝]",
          "price": "6500円～8800円",
          "time": "（ 05:00～15:00 滞在時間10時間 ）"
        }
      ],
      "延長料金": [
        {
          "title": "[全日]",
          "price": "1500円",
          "time": ""
        }
      ]
    },
    "reviews": [
      "部屋が広くて、テーブルとベットが、おいてあっても、まだ隙間がありました\n\nお風呂は、スペースもバスタブもとても広かったです。二人でゆっくりつかれそう。\n部屋も綺麗。このお値段でこの広さなら、かなりお得です。\n　\nただ、トイレの明かりのスイッチと、バスローブがどこかが少し分かりづらかったです（バスローブはラッピングされてる）",
      "先日初めて利用しました。\n口コミで受付が〜と言われていたので心配していましたが、普通の接客で良かったです。\nラブホテルなのでサバサバしていたほうが良いのかもしれません。\n\n部屋は普通のホテルくらいに綺麗で清掃されていて良かったです。\n部屋によると思いますが多摩川が一望出来ました。"
    ]
  },
  {
    "id": "98c291d2-5084-40aa-90ca-4997eec89b70",
    "hotel_name": "NUDA by H-SEVEN (ヌーダ バイ エイチセブン) / 横浜市中区",
    "amenities": [],
    "prices": {},
    "reviews": []
  },
  {
    "id": "276c9315-1fa4-41e5-bce9-68e4b6200a64",
    "hotel_name": "ホテル ひこうせん",
    "amenities": [
      "持込用冷蔵庫",
      "電子レンジ",
      "電気ポット",
      "加湿器※一部",
      "空気清浄機",
      "マッサージチェア※一部",
      "ジェット・バブルバス※一部",
      "マット※一部",
      "ウォシュレット",
      "露天風呂※一部",
      "ミストサウナ",
      "ホームシアター",
      "VOD",
      "Wi-Fi",
      "Android充電器",
      "iPhone充電器",
      "DVDプレーヤー",
      "ブルーレイプレーヤー",
      "セレクトシャンプー※一部",
      "カールドライヤー※一部"
    ],
    "prices": {
      "宿泊": [
        {
          "title": "[平日・日・祝]",
          "price": "5490円～7480円",
          "time": "（ 20:00～翌12:00 ）"
        },
        {
          "title": "[土・祝前]",
          "price": "5990円～7980円",
          "time": "（ 20:00～翌11:00 ）"
        }
      ],
      "休憩": [
        {
          "title": "[全日]",
          "price": "3650円～4660円",
          "time": "（ 06:00～24:00 滞在時間3時間 ）"
        }
      ],
      "サービスタイム": [
        {
          "title": "[平日1部]",
          "price": "4390円～5370円",
          "time": "（ 06:00～18:00 ）"
        },
        {
          "title": "[平日2部]",
          "price": "4390円～5370円",
          "time": "（ 17:00～23:30 ）"
        },
        {
          "title": "[土・日・祝前・祝1部]",
          "price": "4890円～5670円",
          "time": "（ 06:00～18:00 ）"
        },
        {
          "title": "[土・日・祝前・祝2部]",
          "price": "4890円～5670円",
          "time": "（ 17:00～23:30 ）"
        }
      ],
      "延長料金": [
        {
          "title": "[全日]",
          "price": "920円",
          "time": ""
        }
      ]
    },
    "reviews": []
  },
  {
    "id": "6e9fb33f-c511-4543-9221-4f82e4f4b3d2",
    "hotel_name": "ホテル グランバリ リゾート 川崎",
    "amenities": [
      "持込用冷蔵庫",
      "電子レンジ",
      "電気ポット",
      "空気清浄機",
      "ウォシュレット",
      "VOD",
      "Wi-Fi",
      "Android充電器※一部",
      "iPhone充電器※一部",
      "セレクトシャンプー",
      "カールドライヤー※一部",
      "ヘアアイロン※一部",
      "3名以上利用可※一部",
      "1名利用可",
      "ウェルカムドリンクとしてミネラルウォーターお一人様一本セルフサービスしております。",
      "カールドライヤー、ヘアアイロン、各種シャンプー、携帯電話充電器、ブルーレイプレイヤーなどフロントにてお貸出し致します。",
      "その他、無料レンタル品も多数ご用意しております。",
      "お気軽にフロント迄お申し出ください。"
    ],
    "prices": {
      "宿泊": [
        {
          "title": "[日～木・祝]",
          "price": "7600円",
          "time": "（ 18:00～翌12:00 最大18時間 ）"
        },
        {
          "title": "[金・土・祝前]",
          "price": "9800円",
          "time": "（ 20:00～翌11:00 最大15時間 ）"
        }
      ],
      "休憩": [
        {
          "title": "[月～木]",
          "price": "3200円",
          "time": "（ 24時間制 滞在時間2時間 ）"
        },
        {
          "title": "[月～木]",
          "price": "4200円",
          "time": "（ 24時間制 滞在時間3時間 ）"
        },
        {
          "title": "[月～木]",
          "price": "5000円",
          "time": "（ 24時間制 滞在時間4時間 ）"
        },
        {
          "title": "[金・土・日・祝前・祝]",
          "price": "4500円",
          "time": "（ 24時間制 滞在時間2時間 ）"
        },
        {
          "title": "[金・土・日・祝前・祝]",
          "price": "5500円",
          "time": "（ 24時間制 滞在時間3時間 ）"
        },
        {
          "title": "[金・土・日・祝前・祝]",
          "price": "6500円",
          "time": "（ 24時間制 滞在時間4時間 ）"
        }
      ],
      "サービスタイム": [
        {
          "title": "[月～金1部（祝日除く）]",
          "price": "5800円",
          "time": "（ 05:00～16:00 滞在時間11時間 ）"
        },
        {
          "title": "[月～金2部（祝日除く）]",
          "price": "5800円",
          "time": "（ 11:00～19:00 滞在時間8時間 ）"
        },
        {
          "title": "[金・土・日・祝前・祝]",
          "price": "6800円",
          "time": "（ 05:00～16:00 滞在時間11時間 ）"
        }
      ],
      "延長料金": [
        {
          "title": "[全日]",
          "price": "1500円",
          "time": ""
        }
      ]
    },
    "reviews": [
      "オープンしてすぐって書いてあったので試しに行ってみました！値段が安くシンプルな感じの部屋でよかったです！ちょっと使いにいいホテルだと思います！"
    ]
  },
  {
    "id": "5da05c66-61ba-4257-9414-2797112df60d",
    "hotel_name": "HOTEL GOLD 川崎",
    "amenities": [
      "持込用冷蔵庫※一部",
      "電子レンジ",
      "電気ポット",
      "加湿器※一部",
      "空気清浄機※一部",
      "お姫様(天蓋)ベッド※一部",
      "水中照明",
      "ジェット・バブルバス",
      "マット※一部",
      "ウォシュレット",
      "VOD",
      "Wi-Fi",
      "有線LAN",
      "Android充電器",
      "iPhone充電器",
      "DVDプレーヤー",
      "ブルーレイプレーヤー※一部",
      "セレクトシャンプー",
      "カールドライヤー※一部",
      "ヘアアイロン"
    ],
    "prices": {
      "宿泊": [
        {
          "title": "[日～木・祝]",
          "price": "7800円～13300円",
          "time": "（ 17:00～翌11:00 12時間の宿泊滞在保証 ）"
        },
        {
          "title": "[金・土・祝前]",
          "price": "9800円～15500円",
          "time": "（ 19:00～翌11:00 1時以降のチェックインは10時間滞在保証 ）"
        }
      ],
      "休憩": [
        {
          "title": "[月～木 ショート]",
          "price": "3500円～5900円",
          "time": "（ 06:00～翌03:00 滞在時間2時間 ）"
        },
        {
          "title": "[金・土・日・祝]",
          "price": "3500円～5900円",
          "time": "（ 06:00～翌03:00 滞在時間2時間 ）"
        }
      ],
      "フリータイム": [
        {
          "title": "[月～木1部]",
          "price": "5500円～8000円",
          "time": "（ 06:00～18:00 ）"
        },
        {
          "title": "[月～木2部]",
          "price": "5500円～8000円",
          "time": "（ 12:00～22:00 ）"
        },
        {
          "title": "[月～木3部 ]",
          "price": "5500円～8000円",
          "time": "（ 16:00～翌02:00 ）"
        },
        {
          "title": "[金・土・祝前・日・祝1部]",
          "price": "5500円～8000円",
          "time": "（ 06:00～17:00 ）"
        },
        {
          "title": "[金・土・祝前・日・祝2部]",
          "price": "5500円～8000円",
          "time": "（ 12:00～21:00 ）"
        },
        {
          "title": "[金・土・祝前・日・祝3部]",
          "price": "5500円～8000円",
          "time": "（ 16:00～翌01:00 ）"
        }
      ],
      "延長料金": [
        {
          "title": "[全日]",
          "price": "1100円",
          "time": ""
        }
      ]
    },
    "reviews": [
      "受付の年配の女性が表記されている金額(9180円)ではなく、\n15000円を払わしてきた。\nしかも現地決済と選択していたのにも関わらず、\nもう払ってますよね？と威圧的な態度で対応してきた。\n非常に腹立たしく不愉快だ。\nもう二度と行きたくないあんなホテル。",
      "受付のおばちゃんは他の方も書かれていたので想定内。\n\n部屋の清掃がアカン！\n\n下にもお風呂にも長い髪の毛が\nあと、3階のあるお部屋は携帯の電波悪すぎ。\nドコモでやっと1本立つか立たないか。ソフトバンク\n楽天"
    ]
  },
  {
    "id": "d3813241-3cff-490a-84e3-75116947fce0",
    "hotel_name": "ホテル サティス 柏インター",
    "amenities": [],
    "prices": {},
    "reviews": [
      "SARAさんからSATISさんに変わりましたが内装　料金　サービス内容に大きな変化は無く安心しました。前回利用時にお部屋の煌びやかさ浴室　美容家電のレンタル品の豊富さ通信カラオケの音響の良さがとても良かったので再利用しました。\n　今回はサイトでのお部屋選びの際　鰐のオブジェに惹かれ207号室をサービスタイム利用。入室するとベッドとリビングスペースの間の床の強化ガラスの中に河を模した装飾がされ橋が掛かりその上で鰐さんが大きな口を開け迎えてくれました。壁の一面やベッドサイド　内扉にも鏡やガラスの装飾が施され溜息が出るほどに美しい内装でした。浴室も本格ミストサウナ設備があり浴槽も大きく鏡が一面に張られ贅沢バスタイムを楽しめました。スキンケアアメニティもボトルの他にパウチが豊富でレンタルの美容家電でセルフエステ。コスプレ衣装でカラオケを気分良く歌い入浴とエステのルーティン。\n　利用前の問い合わせにもフロント業務の男性スタッフさんがとても丁寧にご案内下さり女性1人利用でも安心して優雅な時間を過ごせました。\n　只　ホテルさんの範疇では無いのですが最寄りバス停からの道のりに街灯や民家が一切無い箇所があり帰りはかなり怖かったです。\n　自宅から往復4時間掛かり帰りの道中は怖かったりもしますがそれでもまた利用させて頂きたいと思える素敵なホテルでした。",
      "LINEクーポンでデラックスタイプ221号室を利用\n事前の電話予約から対面業務　滞在中の問い合わせ等　常に丁寧にご対応下さいました。\n　お部屋は黒を基調に重厚なソファー　ガラステーブルやベッドサイドにガラス細工やアクセサリーが散りばめられ床にも艶かしいオブジェが強化ガラスの中に飾られ淫靡な雰囲気を演出　リビングとベッドルームがレザー調の壁で半分仕切られどちらにも大型TVが設置され　ベッドルームは鏡張りになっておりリリアン素材のカーテンで覆われリビングの壁はファーや煌めくタイル張り　レンジや冷蔵庫の家電はすべて扉付きのラックに収納され日常を忘れさせてくれる素敵過ぎる内装。\n　浴室も広く専用のエアコンが設置されTV付き　楕円形の大きな浴槽はブロア照明機能付き　マットはありませんでしたが2人で充分に入浴を楽しめます。\n　洗面所のスキンケアアメニティもパウチとボトルで豊富に用意されドライヤーも用途に応じて3種　滅菌庫の様な引き出しに収納されてました。\n　カラオケの音量音響は調節可能　美容家電等の無料レンタル品も豊富　ウエルカムサービスはフード　スイーツ　ドリンクから選べ非対面で受け取れます。今回はキンキンに冷えた生ビールと揚げたてサクサクの唐揚げを美味しく頂きました。\n　女性1人利用でもお部屋の内装や浴室　設備　各サービス　お食事と総てに於いて非の打ち所がない素敵な時間を楽しく過ごせました。\n　オーナーさんが変わられたそうですがこれからの更なる展開も楽しみにしております。\n　また必ず利用させて頂きます。ありがとうございました！"
    ]
  }
]